pyckup/__init__.py
pyckup/base.py
pyckup-0.0.6.dist-info/LICENSE
pyckup-0.0.6.dist-info/METADATA
pyckup-0.0.6.dist-info/WHEEL
pyckup-0.0.6.dist-info/top_level.txt
pyckup-0.0.6.dist-info/RECORD
