Metadata-Version: 2.1
Name: pyckup
Version: 0.0.6
Summary: Tools to provide easy access to prepared data to data scientists that can't be asked.
Home-page: https://github.com/i2mint/creek
Author: Otosense
License: apache-2.0
Keywords: data,data access,data preparation,machine learning,artificial intelligence
Platform: any
Requires-Dist: py2store
Requires-Dist: requests
Requires-Dist: haggle
Requires-Dist: graze
